laminar/__init__.py
laminar/components.py
laminar/exceptions.py
laminar/settings.py
laminar/types.py
laminar/version.py
laminar/configurations/__init__.py
laminar/configurations/datastores.py
laminar/configurations/executors.py
laminar/configurations/flows.py
laminar/configurations/layers.py
laminar/configurations/schedulers.py
laminar/configurations/serde.py
laminar/configurations/hooks/__init__.py
laminar/configurations/hooks/annotation.py
laminar/configurations/hooks/condition.py
laminar/configurations/hooks/event.py
laminar/utils/__init__.py
laminar/utils/contexts.py
laminar/utils/fs.py
laminar-2022.5a1.dist-info/LICENSE
laminar-2022.5a1.dist-info/METADATA
laminar-2022.5a1.dist-info/WHEEL
laminar-2022.5a1.dist-info/top_level.txt
laminar-2022.5a1.dist-info/RECORD
